{"path":"/users/7151d57d-6590-47f6-965c-9eaa5967c4ed (PATCH)","status":400,"summary":"Bad request","description":"The request operation could not be completed because a bad argument value was provided.  Please consult the API documentation for further information","details":"[{\"message\":\"The property termsAcceptedTs contains an invalid value (null): termsAcceptedTs is required\"},{\"message\":\"The property termsVersion contains an invalid value (null): may not be empty\"},{\"message\":\"The property originAccountCreatedTs contains an invalid value (null): may not be null\"},{\"message\":\"The property termsVersion contains an invalid value (null): termsVersion is required\"}]","created":1527692304648,"requestId":"b3m67a14fbkrul4sqgig","message":"[{\"message\":\"The property termsAcceptedTs contains an invalid value (null): termsAcceptedTs is required\"},{\"message\":\"The property termsVersion contains an invalid value (null): may not be empty\"},{\"message\":\"The property originAccountCreatedTs contains an invalid value (null): may not be null\"},{\"message\":\"The property termsVersion contains an invalid value (null): termsVersion is required\"}]"}
